iformat/__init__.py
iformat-0.3.3.dist-info/METADATA
iformat-0.3.3.dist-info/WHEEL
iformat-0.3.3.dist-info/licenses/LICENSE
iformat-0.3.3.dist-info/RECORD
