Metadata-Version: 2.1
Name: iformat
Version: 0.3.3
Summary: Indents and pretty prints data structures
Project-URL: Homepage, https://github.com/FinnE145/iprint
Project-URL: Bug Tracker, https://github.com/FinnE145/iprint/issues
Author-email: Finn Emmerson <finne014@gmail.com>
License-File: LICENSE
Classifier: License :: OSI Approved :: GNU Affero General Public License v3
Classifier: Operating System :: OS Independent
Classifier: Programming Language :: Python :: 3
Requires-Python: >=3.7
